ansys/tools/filetransfer/__init__.py
ansys/tools/filetransfer/_client.py
ansys/tools/filetransfer/_log.py
ansys/tools/filetransfer/py.typed
ansys_tools_filetransfer-0.1.1.dist-info/AUTHORS
ansys_tools_filetransfer-0.1.1.dist-info/LICENSE
ansys_tools_filetransfer-0.1.1.dist-info/METADATA
ansys_tools_filetransfer-0.1.1.dist-info/WHEEL
ansys_tools_filetransfer-0.1.1.dist-info/RECORD
