Metadata-Version: 2.1
Name: ansys-tools-filetransfer
Version: 0.1.1
Summary: A Python client for uploading and downloading files via gRPC.
Home-page: https://github.com/ansys/ansys-tools-filetransfer
License: MIT
Author: ANSYS, Inc.
Author-email: pyansys.core@ansys.com
Maintainer: ANSYS, Inc.
Maintainer-email: pyansys.core@ansys.com
Requires-Python: >=3.10,<4.0
Classifier: Development Status :: 5 - Production/Stable
Classifier: License :: OSI Approved :: MIT License
Classifier: Operating System :: OS Independent
Classifier: Programming Language :: Python :: 3
Classifier: Programming Language :: Python :: 3.10
Classifier: Programming Language :: Python :: 3.11
Classifier: Programming Language :: Python :: 3.12
Classifier: Programming Language :: Python :: 3.13
Requires-Dist: ansys-api-tools-filetransfer (>=0.1.0,<0.2.0)
Requires-Dist: grpcio (>=1.17)
Project-URL: Repository, https://github.com/ansys/ansys-tools-filetransfer
